djorum/__init__.py
djorum/admin.py
djorum/forms.py
djorum/models.py
djorum/urls.py
djorum/views.py
djorum/static/css/djorum.css
djorum/static/js/djorum.js
djorum/templates/djorum/templates/djorum/index.html
djorum/templates/djorum/templates/djorum/new_post.html
djorum/templates/djorum/templates/djorum/new_topic.html
djorum/templates/djorum/templates/djorum/post.html
djorum/templates/djorum/templates/djorum/post_confirm_delete.html
djorum/templates/djorum/templates/djorum/post_list.html
djorum/templates/djorum/templates/djorum/topic_confirm_delete.html
djorum/templates/djorum/templates/djorum/topic_update_form.html
djorum-0.0.1.dist-info/DESCRIPTION.rst
djorum-0.0.1.dist-info/METADATA
djorum-0.0.1.dist-info/metadata.json
djorum-0.0.1.dist-info/RECORD
djorum-0.0.1.dist-info/top_level.txt
djorum-0.0.1.dist-info/WHEEL
