Metadata-Version: 2.0
Name: djorum
Version: 0.0.1
Summary: Simple Django Forum
Home-page: https://github.com/andrewblaney/djorum
Author: Andrew Blaney
Author-email: andrewblaney6@gmail.com
License: BSD
Keywords: djorum
Platform: UNKNOWN
Classifier: Development Status :: 3 - Alpha
Classifier: Framework :: Django
Classifier: Intended Audience :: Developers
Classifier: License :: OSI Approved :: BSD License
Classifier: Natural Language :: English
Classifier: Programming Language :: Python :: 2
Classifier: Programming Language :: Python :: 2.7
Classifier: Programming Language :: Python :: 3
Classifier: Programming Language :: Python :: 3.3
Classifier: Programming Language :: Python :: 3.4
Requires-Dist: django-mptt (==0.7.4)
Requires-Dist: django-autoslug (==1.8.0)
